ApiTestEngine/__init__.py
ApiTestEngine/core/__init__.py
ApiTestEngine/core/cases.py
ApiTestEngine/core2/DBClient.py
ApiTestEngine/core2/__init__.py
ApiTestEngine/core2/cases.py
ApiTestEngine/core2/runner.py
ApiTestEngine/core2/tools.py
ApiTestEngine-1.1.5.dist-info/METADATA
ApiTestEngine-1.1.5.dist-info/WHEEL
ApiTestEngine-1.1.5.dist-info/top_level.txt
ApiTestEngine-1.1.5.dist-info/RECORD
