Metadata-Version: 2.1
Name: ApiTestEngine
Version: 1.1.5
Home-page: https://github.com/musen123/unittest-ApiTestEngine
Author: MuSen
Author-email: musen_nmb@qq.com
Classifier: Programming Language :: Python :: 3
Requires-Python: >=3.7
Requires-Dist: Faker (>=13.4.0)
Requires-Dist: jsonpath (>=0.82.2)
Requires-Dist: pymysql (>=1.1.1)
Requires-Dist: requests-toolbelt (>=0.9.1)
Requires-Dist: rsa (>=4.8)
